src/apps.py
centopy/__init__.py
centopy/__main__.py
centopy/base.py
centopy/core.py
centopy/settings.py
centopy/utils.py
src/cli.py
centopy-0.3.0.dist-info/METADATA
centopy-0.3.0.dist-info/WHEEL
centopy-0.3.0.dist-info/entry_points.txt
centopy-0.3.0.dist-info/RECORD
