Metadata-Version: 2.1
Name: centopy
Version: 0.3.0
Summary: Python package for managing file creation and loading
License: None
Author: Vagner Bessa
Author-email: bessavagner@gmail.com
Requires-Python: >=3.10,<4.0
Classifier: License :: Other/Proprietary License
Classifier: Programming Language :: Python :: 3
Classifier: Programming Language :: Python :: 3.10
Classifier: Programming Language :: Python :: 3.11
Requires-Dist: click (>=8.1.3,<9.0.0)
